{
"cyclic:crystal_axe":{
        "distracted": "1.1",
        "unaware": "1.2"
    },
"cyclic:crystal_hoe":{
        "distracted": "1.2",
        "unaware": "1.4"
    },
"cyclic:crystal_pickaxe":{
        "distracted": "1.4",
        "unaware": "2"
    },
"cyclic:crystal_shovel":{
        "distracted": "1.1",
        "unaware": "1.2"
    },
"cyclic:crystal_sword":{
        "distracted": "1.25",
        "unaware": "1.5"
    },
"cyclic:emerald_axe":{
        "distracted": "1.1",
        "unaware": "1.2"
    },
"cyclic:emerald_hoe":{
        "distracted": "1.2",
        "unaware": "1.4"
    },
"cyclic:emerald_pickaxe":{
        "distracted": "1.4",
        "unaware": "2"
    },
"cyclic:emerald_shovel":{
        "distracted": "1.1",
        "unaware": "1.2"
    },
"cyclic:emerald_sword":{
        "distracted": "1.25",
        "unaware": "1.5"
    },
"cyclic:netherbrick_axe":{
        "distracted": "1.1",
        "unaware": "1.2"
    },
"cyclic:netherbrick_hoe":{
        "distracted": "1.2",
        "unaware": "1.4"
    },
"cyclic:netherbrick_pickaxe":{
        "distracted": "1.4",
        "unaware": "2"
    },
"cyclic:netherbrick_shovel":{
        "distracted": "1.1",
        "unaware": "1.2"
    },
"cyclic:netherbrick_sword":{
        "distracted": "1.25",
        "unaware": "1.5"
    },
"cyclic:sandstone_axe":{
        "distracted": "1.1",
        "unaware": "1.2"
    },
"cyclic:sandstone_hoe":{
        "distracted": "1.2",
        "unaware": "1.4"
    },
"cyclic:sandstone_pickaxe":{
        "distracted": "1.4",
        "unaware": "2"
    },
"cyclic:sandstone_shovel":{
        "distracted": "1.1",
        "unaware": "1.2"
    },
"cyclic:sandstone_sword":{
        "distracted": "1.25",
        "unaware": "1.5"
    }
}
